django_url_breadcrumbs-0.3.3.dist-info/METADATA
django_url_breadcrumbs-0.3.3.dist-info/top_level.txt
django_url_breadcrumbs-0.3.3.dist-info/pydist.json
django_url_breadcrumbs-0.3.3.dist-info/RECORD
django_url_breadcrumbs-0.3.3.dist-info/WHEEL
django_url_breadcrumbs-0.3.3.dist-info/DESCRIPTION.rst
urlbreadcrumbs/__init__.py
urlbreadcrumbs/conf.py
urlbreadcrumbs/models.py
urlbreadcrumbs/context_processors.py
urlbreadcrumbs/url_hacks.py
urlbreadcrumbs/templatetags/__init__.py
urlbreadcrumbs/templatetags/urlbreadcrumbs_tags.py
urlbreadcrumbs/tests/__init__.py
urlbreadcrumbs/tests/settings.py
urlbreadcrumbs/tests/test_base.py
urlbreadcrumbs/tests/models.py
urlbreadcrumbs/tests/views.py
urlbreadcrumbs/tests/urls.py
urlbreadcrumbs/templates/urlbreadcrumbs/default.html
urlbreadcrumbs/templates/urlbreadcrumbs/twitter-bootstrap.html
