Metadata-Version: 2.0
Name: django-url-breadcrumbs
Version: 0.3.3
Summary: a generic app to provide a simple breadcrumbs functionality in django projects
Home-page: https://bitbucket.org/slafs/django-url-breadcrumbs/
Author: Slawek Ehlert
Author-email: slafs@op.pl
License: BSD
Platform: UNKNOWN
Classifier: Development Status :: 4 - Beta
Classifier: Environment :: Web Environment
Classifier: Framework :: Django
Classifier: Intended Audience :: Developers
Classifier: License :: OSI Approved :: BSD License
Classifier: Operating System :: OS Independent
Classifier: Programming Language :: Python
Classifier: Programming Language :: Python :: 2
Classifier: Programming Language :: Python :: 2.6
Classifier: Programming Language :: Python :: 2.7
Classifier: Programming Language :: Python :: 3
Classifier: Programming Language :: Python :: 3.2
Classifier: Topic :: Utilities
